capx_core/__init__.py
capx_core/detection_3x3.py
capx_core/detection_4x4.py
capx_core/detector.py
capx_core/model_downloader.py
capx_core/models.py
capx_core/targets.py
capx_core/utils.py
capx_core-1.0.1.dist-info/licenses/LICENSE
capx_core-1.0.1.dist-info/METADATA
capx_core-1.0.1.dist-info/WHEEL
capx_core-1.0.1.dist-info/top_level.txt
capx_core-1.0.1.dist-info/RECORD
