Metadata-Version: 2.4
Name: capx-core
Version: 1.0.1
Summary: Core AI engine for solving reCAPTCHA image challenges
Author-email: Mahdi Marjani <mahdi.marjani.dev@gmail.com>
License-Expression: MIT
Project-URL: Homepage, https://github.com/mahdi-marjani/capx-core
Project-URL: Documentation, https://github.com/mahdi-marjani/capx-core
Project-URL: Repository, https://github.com/mahdi-marjani/capx-core.git
Project-URL: Issues, https://github.com/mahdi-marjani/capx-core/issues
Requires-Python: >=3.8
License-File: LICENSE
Requires-Dist: numpy>=2.2.6
Requires-Dist: opencv-python>=4.12.0.88
Requires-Dist: requests>=2.32.5
Requires-Dist: ultralytics>=8.3.241
Requires-Dist: tqdm>=4.67.1
Dynamic: license-file
